validoc/__init__.py
validoc/__main__.py
validoc/cli.py
validoc/constants.py
validoc/executor.py
validoc/models.py
validoc/parser.py
validoc/reporter.py
validoc/runner.py
validoc-0.1.2.dist-info/WHEEL
validoc-0.1.2.dist-info/entry_points.txt
validoc-0.1.2.dist-info/METADATA
validoc-0.1.2.dist-info/RECORD
