Metadata-Version: 2.3
Name: validoc
Version: 0.1.2
Summary: Executable tutorial testing - make documentation tutorials runnable as tests
Author: Stefane Fermigier
Author-email: Stefane Fermigier <sf@abilian.com>
Requires-Dist: pyyaml>=6.0
Requires-Python: >=3.12
Project-URL: Homepage, https://github.com/abilian/validoc
Project-URL: Issues, https://github.com/abilian/validoc/issues
Project-URL: Repository, https://github.com/abilian/validoc
